internetofutils/__init__.py
internetofutils/idl.py
internetofutils/rndb.py
internetofutils-0.1.0.dist-info/METADATA
internetofutils-0.1.0.dist-info/WHEEL
internetofutils-0.1.0.dist-info/top_level.txt
internetofutils-0.1.0.dist-info/RECORD
