Metadata-Version: 2.1
Name: internetofutils
Version: 0.1.0
Summary: A utility package with various things in it.
Home-page: https://gitlab.com/cjmatthy200/InternetOfUtilities/
Author: matthyno
Author-email: cjmatthy200@gmail.com
License: UNKNOWN
Platform: UNKNOWN
Classifier: Programming Language :: Python :: 3
Classifier: Operating System :: OS Independent
Requires-Python: >=3.6
